pyRealtor/__init__.py
pyRealtor/facade.py
pyRealtor/geo.py
pyRealtor/housingCom.py
pyRealtor/proxy.py
pyRealtor/realtor.py
pyRealtor/realtorCa.py
pyRealtor/realtorCom.py
pyRealtor/realtorFactory.py
pyRealtor/report.py
pyRealtor/config/column_mapping_cfg.json
pyRealtor/config/column_mapping_cfg_housing_com.json
pyRealtor/config/column_mapping_cfg_housing_com_rent.json
pyRealtor/config/column_mapping_cfg_realtor_ca_agri.json
pyRealtor/config/column_mapping_cfg_realtor_com.json
pyRealtor/config/graphql_queries.yml
pyRealtor/config/graphql_queries_housing.yml
pyrealtor-0.2.6.dist-info/licenses/LICENSE.md
pyrealtor-0.2.6.dist-info/METADATA
pyrealtor-0.2.6.dist-info/WHEEL
pyrealtor-0.2.6.dist-info/top_level.txt
pyrealtor-0.2.6.dist-info/RECORD
