Metadata-Version: 2.4
Name: pyRealtor
Version: 0.2.6
Summary: Python package for fetching and analyzing REALTOR.CA and REALTOR.COM MLS Listings
Home-page: https://github.com/rachitt96/pyRealtor
Author: Rachit Trivedi
Author-email: rachitt96@gmail.com
License: MIT
Classifier: Programming Language :: Python :: 3
Classifier: Operating System :: OS Independent
Requires-Python: >=3.6
License-File: LICENSE.md
Requires-Dist: requests>=2.26.0
Requires-Dist: pandas>=1.3.5
Requires-Dist: numpy>=1.21.4
Requires-Dist: openpyxl>=3.1.2
Requires-Dist: lxml>=5.1.0
Requires-Dist: pyyaml>=6.0.1
Dynamic: author
Dynamic: author-email
Dynamic: classifier
Dynamic: description
Dynamic: description-content-type
Dynamic: home-page
Dynamic: license
Dynamic: license-file
Dynamic: requires-dist
Dynamic: requires-python
Dynamic: summary
